odoo8_addon_project_model_to_task-8.0.0.5.0.99.dev18-py3.8-nspkg.pth
odoo_addons/project_model_to_task/README.rst
odoo_addons/project_model_to_task/__init__.py
odoo_addons/project_model_to_task/__openerp__.py
odoo_addons/project_model_to_task/action.py
odoo_addons/project_model_to_task/project.py
odoo_addons/project_model_to_task/project_view.xml
odoo_addons/project_model_to_task/i18n/ar.po
odoo_addons/project_model_to_task/i18n/ca.po
odoo_addons/project_model_to_task/i18n/de.po
odoo_addons/project_model_to_task/i18n/el.po
odoo_addons/project_model_to_task/i18n/es.po
odoo_addons/project_model_to_task/i18n/es_CR.po
odoo_addons/project_model_to_task/i18n/es_MX.po
odoo_addons/project_model_to_task/i18n/es_VE.po
odoo_addons/project_model_to_task/i18n/fi.po
odoo_addons/project_model_to_task/i18n/fr.po
odoo_addons/project_model_to_task/i18n/gl.po
odoo_addons/project_model_to_task/i18n/hr.po
odoo_addons/project_model_to_task/i18n/hr_HR.po
odoo_addons/project_model_to_task/i18n/hu.po
odoo_addons/project_model_to_task/i18n/it.po
odoo_addons/project_model_to_task/i18n/ja.po
odoo_addons/project_model_to_task/i18n/lt.po
odoo_addons/project_model_to_task/i18n/lv.po
odoo_addons/project_model_to_task/i18n/mk.po
odoo_addons/project_model_to_task/i18n/mn.po
odoo_addons/project_model_to_task/i18n/nl.po
odoo_addons/project_model_to_task/i18n/pl.po
odoo_addons/project_model_to_task/i18n/project_model_to_task.pot
odoo_addons/project_model_to_task/i18n/pt.po
odoo_addons/project_model_to_task/i18n/pt_BR.po
odoo_addons/project_model_to_task/i18n/pt_PT.po
odoo_addons/project_model_to_task/i18n/ro.po
odoo_addons/project_model_to_task/i18n/sl.po
odoo_addons/project_model_to_task/i18n/sv.po
odoo_addons/project_model_to_task/i18n/tr.po
odoo_addons/project_model_to_task/i18n/tr_TR.po
odoo_addons/project_model_to_task/i18n/uk.po
odoo_addons/project_model_to_task/i18n/zh_CN.po
odoo_addons/project_model_to_task/static/description/icon.png
odoo8_addon_project_model_to_task-8.0.0.5.0.99.dev18.dist-info/METADATA
odoo8_addon_project_model_to_task-8.0.0.5.0.99.dev18.dist-info/WHEEL
odoo8_addon_project_model_to_task-8.0.0.5.0.99.dev18.dist-info/namespace_packages.txt
odoo8_addon_project_model_to_task-8.0.0.5.0.99.dev18.dist-info/top_level.txt
odoo8_addon_project_model_to_task-8.0.0.5.0.99.dev18.dist-info/RECORD
