Metadata-Version: 2.1
Name: odoo8-addon-project-model-to-task
Version: 8.0.0.5.0.99.dev18
Summary: Project Model to Task
Home-page: https://www.akretion.com
Author: Akretion, Odoo Community Association (OCA)
Author-email: support@odoo-community.org
License: UNKNOWN
Platform: UNKNOWN
Classifier: Programming Language :: Python
Classifier: Framework :: Odoo
Classifier: Framework :: Odoo :: 8.0
Requires-Python: ~=2.7
Requires-Dist: odoo (<9.0a,>=8.0a)
